eppconvert/__init__.py
eppconvert/eppformat.py
eppconvert/eppread.py
eppconvert/gpx2epp.py
eppconvert/release.py
eppconvert-0.9.3.dist-info/LICENSE
eppconvert-0.9.3.dist-info/METADATA
eppconvert-0.9.3.dist-info/WHEEL
eppconvert-0.9.3.dist-info/entry_points.txt
eppconvert-0.9.3.dist-info/top_level.txt
eppconvert-0.9.3.dist-info/RECORD
